PayOkApiPy/payok.py
payokapipy-1.0.2.dist-info/METADATA
payokapipy-1.0.2.dist-info/WHEEL
payokapipy-1.0.2.dist-info/RECORD
